linestickerdata/__init__.py
linestickerdata/animation.py
linestickerdata/linesticker_animation.csv
linestickerdata-0.1.16.dist-info/LICENSE.txt
linestickerdata-0.1.16.dist-info/METADATA
linestickerdata-0.1.16.dist-info/WHEEL
linestickerdata-0.1.16.dist-info/top_level.txt
linestickerdata-0.1.16.dist-info/zip-safe
linestickerdata-0.1.16.dist-info/RECORD
