Metadata-Version: 2.1
Name: linestickerdata
Version: 0.1.16
Summary: repo to get line sticker data
Home-page: https://github.com/steerapi/line-sticker-data
Author: Surat Teerapittayanon
Author-email: steerapi@gmail.com
License: MIT
Platform: UNKNOWN
